htmlextradata/__init__.py
htmlextradata/plugin.py
htmlextradata-0.1.4.dist-info/METADATA
htmlextradata-0.1.4.dist-info/WHEEL
htmlextradata-0.1.4.dist-info/entry_points.txt
htmlextradata-0.1.4.dist-info/RECORD
