Metadata-Version: 2.1
Name: htmlextradata
Version: 0.1.4
Summary: MkDocs Plugin
Home-page: https://github.com/stalexsm/mkdocs-htmlextradata-plugin
License: MIT
Keywords: mkdocs,mkdocs-plugin
Author: Alexandr Starovoytov
Author-email: stalex.info@yandex.ru
Requires-Python: >=3.10,<4.0
Classifier: License :: OSI Approved :: MIT License
Classifier: Programming Language :: Python :: 3
Classifier: Programming Language :: Python :: 3.10
Classifier: Programming Language :: Python :: 3.11
Requires-Dist: mkdocs (>=1.4.0,<2.0.0)
Requires-Dist: pyyaml (>=6.0,<7.0)
Project-URL: Repository, https://github.com/stalexsm/mkdocs-htmlextradata-plugin
